setup.py
psycopg2_dateutils/__init__.py
psycopg2_dateutils/psycopg2_dateutils.py
psycopg2_dateutils.egg-info/PKG-INFO
psycopg2_dateutils.egg-info/SOURCES.txt
psycopg2_dateutils.egg-info/dependency_links.txt
psycopg2_dateutils.egg-info/requires.txt
psycopg2_dateutils.egg-info/top_level.txt