Metadata-Version: 1.0
Name: psycopg2-dateutils
Version: 0.1
Summary: Use dateutils.relativedelta to represent PostgreSQL interval types
Home-page: UNKNOWN
Author: Grzegorz Nosek
Author-email: root@localdomain.pl
License: MIT
Keywords: psycopg2 dateutils postgresql interval
Platform: UNKNOWN
